{"expires":1760438494046,"value":{"code":200,"headers":{"etag":"W/\"aZyhTo1WUE\"","last-modified":"Tue, 07 Oct 2025 10:41:34 GMT","cache-control":"s-maxage=604800, stale-while-revalidate"},"body":{"prefix":"heroicons","lastModified":1758346379,"aliases":{},"width":24,"height":24,"icons":{"bars-3":{"body":"<path fill=\"none\" stroke=\"currentColor\" stroke-linecap=\"round\" stroke-linejoin=\"round\" stroke-width=\"1.5\" d=\"M3.75 6.75h16.5M3.75 12h16.5m-16.5 5.25h16.5\"/>"}}}},"mtime":1759833694397,"integrity":"maX4dISsQJ"}